xposer/__init__.py
xposer/api/__init__.py
xposer/api/base/__init__.py
xposer/api/base/base_fastapi_service.py
xposer/api/base/base_fastapi_service_config_model.py
xposer/api/base/base_kafka_aiolib.py
xposer/api/base/base_kafka_router.py
xposer/api/base/base_kafka_service.py
xposer/api/base/base_kafka_service_config_model.py
xposer/api/base/base_service.py
xposer/api/base/expose_cli.py
xposer/api/base/expose_http.py
xposer/api/base/facade_base_class.py
xposer/api/base/xpcontroller_base_class.py
xposer/api/base/http/__init__.py
xposer/api/base/http/decorators/__init__.py
xposer/api/base/http/decorators/wrap_response_decorator.py
xposer/api/base/http/dto/__init__.py
xposer/api/base/http/dto/request_meta_dto.py
xposer/api/base/http/dto/response_dto.py
xposer/api/base/http/dto/response_wrapper_dto.py
xposer/api/base/http/routes/__init__.py
xposer/api/base/http/routes/debug_routes.py
xposer/core/__init__.py
xposer/core/abstract_facade.py
xposer/core/abstract_handler.py
xposer/core/abstract_xpcontroller.py
xposer/core/boot.py
xposer/core/completed_exception.py
xposer/core/configuration_model.py
xposer/core/configure.py
xposer/core/context.py
xposer/core/coro_exception.py
xposer/core/facade_factory.py
xposer/core/logger.py
xposer/core/xpcontroller_factory.py
xposer/core/xpose_task.py
xposer/models/__init__.py
xposer/models/base_routers_config_model.py
xposer/models/configuration_model.py
xposer/sample_app/__init__.py
xposer/sample_app/http_post_uvicorn_fastapi/__init__.py
xposer/sample_app/http_post_uvicorn_fastapi/sample_app_http.py
xposer/sample_app/http_post_uvicorn_fastapi/sample_app_http_xpcontroller.py
xposer/sample_app/http_post_uvicorn_fastapi/routers/__init__.py
xposer/sample_app/http_post_uvicorn_fastapi/routers/sample_app_http_service.py
xposer/sample_app/rpc_kafka/__init__.py
xposer/sample_app/rpc_kafka/decorator_sample.py
xposer/sample_app/rpc_kafka/sample_app_kafka.py
xposer/sample_app/rpc_kafka/sample_app_kafka_service.py
xposer-1.0.1.dist-info/METADATA
xposer-1.0.1.dist-info/WHEEL
xposer-1.0.1.dist-info/top_level.txt
xposer-1.0.1.dist-info/RECORD
