Metadata-Version: 2.1
Name: xposer
Version: 1.0.1
Summary: Xpose your functions as microservices over arbitrary channels using standardized logging and configuration
Home-page: https://github.com/barocsi/xposer
Author: Aron Barocsi
Author-email: aron.barocsi@gmail.com
License: Private
Keywords: microservice,function wrapper,function exposer
Platform: UNKNOWN
Requires-Dist: annotated-types ==0.5.0
Requires-Dist: anyio ==3.7.1
Requires-Dist: astroid ==2.15.6
Requires-Dist: asttokens ==2.4.0
Requires-Dist: build ==1.2.1
Requires-Dist: certifi ==2023.7.22
Requires-Dist: click ==8.1.7
Requires-Dist: colorama ==0.4.6
Requires-Dist: confluent-kafka ==2.2.0
Requires-Dist: dill ==0.3.7
Requires-Dist: exceptiongroup ==1.1.3
Requires-Dist: executing ==2.0.0
Requires-Dist: fastapi ==0.103.1
Requires-Dist: grpcio ==1.58.0
Requires-Dist: grpcio-tools ==1.58.0
Requires-Dist: h11 ==0.14.0
Requires-Dist: httpcore ==0.18.0
Requires-Dist: httpx ==0.25.0
Requires-Dist: icecream ==2.1.3
Requires-Dist: idna ==3.4
Requires-Dist: isort ==5.12.0
Requires-Dist: lazy-object-proxy ==1.9.0
Requires-Dist: mccabe ==0.7.0
Requires-Dist: nest-asyncio ==1.5.8
Requires-Dist: packaging ==24.0
Requires-Dist: platformdirs ==3.10.0
Requires-Dist: protobuf ==4.24.3
Requires-Dist: psutil ==5.9.5
Requires-Dist: pydantic ==2.3.0
Requires-Dist: pydantic-settings ==2.0.3
Requires-Dist: pydantic-core ==2.6.3
Requires-Dist: Pygments ==2.16.1
Requires-Dist: pylint ==2.17.5
Requires-Dist: pyproject-hooks ==1.0.0
Requires-Dist: python-dotenv ==1.0.0
Requires-Dist: PyYAML ==6.0.1
Requires-Dist: shortuuid ==1.0.11
Requires-Dist: six ==1.16.0
Requires-Dist: sniffio ==1.3.0
Requires-Dist: starlette ==0.27.0
Requires-Dist: tomli ==2.0.1
Requires-Dist: tomlkit ==0.12.1
Requires-Dist: typing-extensions ==4.7.1
Requires-Dist: uvicorn ==0.23.2
Requires-Dist: wrapt ==1.15.0
